riscv_config/__init__.py
riscv_config/checker.py
riscv_config/constants.py
riscv_config/errors.py
riscv_config/isa_validator.py
riscv_config/main.py
riscv_config/schemaValidator.py
riscv_config/utils.py
riscv_config/warl.py
riscv_config/schemas/schema_custom.yaml
riscv_config/schemas/schema_debug.yaml
riscv_config/schemas/schema_isa.yaml
riscv_config/schemas/schema_platform.yaml
riscv_config-3.18.3.dist-info/LICENSE
riscv_config-3.18.3.dist-info/METADATA
riscv_config-3.18.3.dist-info/WHEEL
riscv_config-3.18.3.dist-info/entry_points.txt
riscv_config-3.18.3.dist-info/top_level.txt
riscv_config-3.18.3.dist-info/RECORD
