Metadata-Version: 1.2
Name: riscv_config
Version: 3.18.3
Summary: RISC-V Configuration Validator
Home-page: https://github.com/riscv/riscv-config
Author: InCore Semiconductors Pvt. Ltd.
Author-email: neelgala@incoresemi.com
License: BSD-3-Clause
Platform: UNKNOWN
Classifier: Programming Language :: Python :: 3.6
Classifier: License :: OSI Approved :: BSD License
Classifier: Development Status :: 4 - Beta
Requires-Python: >=3.7.0
